autodistill_grounded_sam/__init__.py
autodistill_grounded_sam/grounded_sam.py
autodistill_grounded_sam/helpers.py
autodistill_grounded_sam-0.1.2.dist-info/LICENSE
autodistill_grounded_sam-0.1.2.dist-info/METADATA
autodistill_grounded_sam-0.1.2.dist-info/WHEEL
autodistill_grounded_sam-0.1.2.dist-info/top_level.txt
autodistill_grounded_sam-0.1.2.dist-info/RECORD
